banet/__init__.py
banet/_nbdev.py
banet/cli.py
banet/core.py
banet/data.py
banet/geo.py
banet/historical.py
banet/models.py
banet/nrt.py
banet/predict.py
banet/train.py
banet/web.py
banet-0.6.7.dist-info/LICENSE
banet-0.6.7.dist-info/METADATA
banet-0.6.7.dist-info/WHEEL
banet-0.6.7.dist-info/entry_points.txt
banet-0.6.7.dist-info/top_level.txt
banet-0.6.7.dist-info/RECORD
