Metadata-Version: 2.1
Name: banet
Version: 0.6.7
Summary: A deep learning approach for mapping and dating burned areas using temporal sequences of satellite images
Home-page: https://github.com/mnpinto/banet
Author: Miguel Pinto
Author-email: mnpinto@fc.ul.pt
License: Apache Software License 2.0
Keywords: burned areas,viirs,deep learning,computer vision,remote sensing
Platform: UNKNOWN
Classifier: Development Status :: 4 - Beta
Classifier: Intended Audience :: Developers
Classifier: License :: OSI Approved :: Apache Software License
Classifier: Natural Language :: English
Classifier: Programming Language :: Python :: 3.6
Classifier: Programming Language :: Python :: 3.7
Classifier: Programming Language :: Python :: 3.8
Requires-Python: >=3.6
Requires-Dist: geoget
Requires-Dist: fire-split
Requires-Dist: fastcore
Requires-Dist: nbdev
Requires-Dist: fastai (==2.2.7)
Requires-Dist: rasterio
Requires-Dist: geopandas
Requires-Dist: shapely
Requires-Dist: netcdf4
Requires-Dist: pyhdf (==0.10.2)
Requires-Dist: proj
Requires-Dist: geos
Requires-Dist: cartopy
